README.md
setup.cfg
setup.py
mailgun/__init__.py
mailgun/api.py
mailgun/base.py
mailgun/ips.py
mailgun/mailing_list.py
mailgun/domain/__init__.py
mailgun/domain/ips.py
mailgun/domain/logs.py
mailgun_python_sdk.egg-info/PKG-INFO
mailgun_python_sdk.egg-info/SOURCES.txt
mailgun_python_sdk.egg-info/dependency_links.txt
mailgun_python_sdk.egg-info/requires.txt
mailgun_python_sdk.egg-info/top_level.txt
tests/__init__.py
tests/test_api.py
tests/test_base.py
tests/test_init.py
tests/test_ips.py
tests/test_mailing_list.py
tests/domain/__init__.py
tests/domain/test_init.py
tests/domain/test_ips.py
tests/domain/test_logs.py