Metadata-Version: 1.2
Name: mailgun-python-sdk
Version: 0.3
Summary: Mailgun Python SDK (unofficial)
Home-page: https://github.com/m-vdb/mailgun-python-sdk
Author: Maxime Vdb
Author-email: me@maxvdb.com
License: MIT
Download-URL: https://github.com/m-vdb/mailgun-python-sdk/archive/v0.3.tar.gz
Project-URL: Source Code, https://github.com/m-vdb/mailgun-python-sdk
Keywords: mailgun api sdk
Platform: UNKNOWN
